README.md
setup.py
abi_guesser/__init__.py
abi_guesser/lib.py
abi_guesser.egg-info/PKG-INFO
abi_guesser.egg-info/SOURCES.txt
abi_guesser.egg-info/dependency_links.txt
abi_guesser.egg-info/requires.txt
abi_guesser.egg-info/top_level.txt