Metadata-Version: 2.1
Name: abi-guesser
Version: 0.3
Summary: Python replication of samczsun's abi-guesser
Home-page: https://github.com/0xSt1ng3R/abi-guesser-py
Author: 0xSt1ng3R
License: UNKNOWN
Platform: UNKNOWN
